BezierInterpolate/interpolate.py
BezierInterpolate-0.0.2.dist-info/LICENSE
BezierInterpolate-0.0.2.dist-info/METADATA
BezierInterpolate-0.0.2.dist-info/WHEEL
BezierInterpolate-0.0.2.dist-info/top_level.txt
BezierInterpolate-0.0.2.dist-info/RECORD
